broker/__init__.py
broker/aws/__init__.py
broker/aws/sts.py
broker/data.py
broker/routes.py
broker/serve.py
broker/utils.py
broker/web/static/scripts/cli.js
broker/web/static/scripts/main.js
broker/web/static/styles/__main__.css
broker/web/static/styles/base.css
broker/web/static/styles/box.css
broker/web/static/styles/profile.css
broker/web/templates/index.html
device/__init__.py
device/auth.py
device/cli.py
device/config.py
device/state.py
device/utils.py
aws_oidc_broker-0.1.0.dist-info/METADATA
aws_oidc_broker-0.1.0.dist-info/entry_points.txt
aws_oidc_broker-0.1.0.dist-info/WHEEL
aws_oidc_broker-0.1.0.dist-info/LICENSE
aws_oidc_broker-0.1.0.dist-info/RECORD
