Metadata-Version: 2.1
Name: aws-oidc-broker
Version: 0.1.0
Summary: 
Keywords: packaging,poetry
Author: Rishang
Requires-Python: >=3.8
Classifier: Programming Language :: Python :: 3
Classifier: Programming Language :: Python :: 3.8
Classifier: Programming Language :: Python :: 3.9
Classifier: Programming Language :: Python :: 3.10
Classifier: Programming Language :: Python :: 3.11
Classifier: Topic :: Software Development :: Build Tools
Classifier: Topic :: Software Development :: Libraries :: Python Modules
Requires-Dist: authlib (>=1.2.0,<2.0.0)
Requires-Dist: boto3 (>=1.26.54,<2.0.0)
Requires-Dist: flask (>=2.2.2,<3.0.0)
Requires-Dist: gunicorn (>=20.1.0,<21.0.0)
Requires-Dist: pyjwt (>=2.6.0,<3.0.0)
Requires-Dist: python-dotenv (>=0.21.1,<0.22.0)
Requires-Dist: requests
Requires-Dist: rich (>=13.2.0,<14.0.0)
Requires-Dist: typer (>=0.7.0,<0.8.0)
